LICENCE
README.md
setup.cfg
setup.py
aws_google_saml/__main__.py
aws_google_saml/authed.html
aws_google_saml.egg-info/PKG-INFO
aws_google_saml.egg-info/SOURCES.txt
aws_google_saml.egg-info/dependency_links.txt
aws_google_saml.egg-info/entry_points.txt
aws_google_saml.egg-info/requires.txt
aws_google_saml.egg-info/top_level.txt