Metadata-Version: 2.1
Name: aws-google-saml
Version: 2024.716.3
Summary: A user-browser driven SAML authentication tool for AWS
Home-page: https://github.com/bengieeee/aws-google-saml
Download-URL: https://github.com/bengieeee/aws-google-saml/archive/refs/tags/0.7.1.tar.gz
Author: bengieeee
License: MIT
Keywords: aws,aws-cli,saml,google,google-saml,google-saml-aws
Classifier: Development Status :: 3 - Alpha
Classifier: Intended Audience :: Developers
Classifier: Topic :: Software Development :: Build Tools
Classifier: License :: OSI Approved :: MIT License
Classifier: Programming Language :: Python :: 3
License-File: LICENCE
Requires-Dist: botocore
Requires-Dist: boto3
